fast_man/__init__.py
fast_man/converter.py
fast_man/utils.py
tests/__init__.py
tests/test_converter.py
fast_man-0.1.9.dist-info/LICENSE
fast_man-0.1.9.dist-info/METADATA
fast_man-0.1.9.dist-info/WHEEL
fast_man-0.1.9.dist-info/entry_points.txt
fast_man-0.1.9.dist-info/top_level.txt
fast_man-0.1.9.dist-info/RECORD
